hashtron/__init__.py
hashtron/classifier/__init__.py
hashtron/classifier/constructor.py
hashtron/classifier/forward.py
hashtron/classifier/model.py
hashtron/classifier/test_forward.py
hashtron/classifier/test_view.py
hashtron/classifier/view.py
hashtron/datasets/__init__.py
hashtron/datasets/mnist/__init__.py
hashtron/datasets/mnist/mnist.py
hashtron/datasets/mnist/test_mnist.py
hashtron/datasets/squareroot/__init__.py
hashtron/datasets/squareroot/api.py
hashtron/datasets/stringhash/__init__.py
hashtron/datasets/stringhash/bytehash.py
hashtron/datasets/stringhash/stringhash.py
hashtron/datasets/stringhash/test_stringhash.py
hashtron/hash/__init__.py
hashtron/hash/hash.py
hashtron/hash/test_hash.py
hashtron/layer/__init__.py
hashtron/layer/combiner.py
hashtron/layer/layer.py
hashtron/layer/full/__init__.py
hashtron/layer/full/combiner.py
hashtron/layer/full/layer.py
hashtron/layer/majpool2d/__init__.py
hashtron/layer/majpool2d/combiner.py
hashtron/layer/majpool2d/layer.py
hashtron/layer/majpool2d/test_combiner.py
hashtron/net/__init__.py
hashtron/net/input.py
hashtron/net/single_value.py
hashtron/net/feedforward/__init__.py
hashtron/net/feedforward/feedforward_network.py
hashtron/net/feedforward/io.py
hashtron/net/feedforward/net.py
hashtron/net/feedforward/test_net.py
hashtron-0.1.0.dist-info/LICENSE
hashtron-0.1.0.dist-info/METADATA
hashtron-0.1.0.dist-info/WHEEL
hashtron-0.1.0.dist-info/top_level.txt
hashtron-0.1.0.dist-info/RECORD
