Metadata-Version: 2.2
Name: hashtron
Version: 0.1.0
Summary: A Python inference-only engine for the hashtron binary classifier
Home-page: https://github.com/neurlang/pyclassifier
Author: Neurlang Project
Author-email: Neurlang Project <77860779+neurlang@users.noreply.github.com>
License: MIT License
Project-URL: Homepage, https://github.com/neurlang/pyclassifier
Project-URL: Documentation, https://hashtron.readthedocs.io/en/latest/
Keywords: binary,classifier,machine-learning,hashtron
Classifier: License :: OSI Approved :: MIT License
Classifier: Programming Language :: Python
Classifier: Programming Language :: Python :: 3
Requires-Python: >=3.6
License-File: LICENSE
Requires-Dist: requests
Dynamic: author
Dynamic: home-page
Dynamic: requires-python
